Workbook

Sheet Inputs
A1: HIVOLT — Unit Economics Model
A2: Fill every YELLOW cell from your Tapstitch account. Blue cells are levers you can change. Black cells are formulas — do not edit.
A4: LEGEND
A5: Yellow fill | B5: You must supply this from Tapstitch (blank cost, print fee, shipping, duty)
A6: Blue text | B6: Assumption / lever — change to run scenarios
A7: Black text | B7: Calculated — leave alone
A9: 1. TAPSTITCH COSTS PER PRODUCT
A10: Pull from Tapstitch > catalog (select US fulfilment region) and their Price Checker tool.
A12: Product | B12: Retail $ | C12: # Blanks | D12: Blank cost ea $ | E12: # Print areas | F12: Print fee/area $ | G12: Ship 1st item $ | H12: Ship addl item $ | I12: Duty + svc fee $ | J12: US fulfil?
A13: Voltcore 2-Piece Set (bra + leggings) | B13: 79 | C13: 2
A14: Women's High-Waisted Flare Leggings | B14: 54 | C14: 1
A15: Women's Twist Front V-Neck Sports Bra | B15: 38 | C15: 1
A16: Men's High-Stretch Gym T-Shirt | B16: 34 | C16: 1
A17: Men's Tapered Leg Drawstring Joggers | B17: 69 | C17: 1
A18: Women's High Rise Yoga Shorts | B18: 42 | C18: 1
A19: Two-Tone Fleeced Varsity Jacket | B19: 69 | C19: 1
A20: EXAMPLE (delete) — Leggings WB0031 | B20: 54 | C20: 1 | D20: 12.5 | E20: 1 | F20: 2.99 | G20: 4.44 | H20: 0.5 | I20: 2 | J20: No
A21: Example values are illustrative only — NOT real Tapstitch prices. Research could not obtain published activewear costs.
A23: 2. STORE ASSUMPTIONS
A24: Assumption | B24: Value | C24: Note
A25: Payment fee % | B25: 0.029 | C25: Shopify Payments US standard ~2.9%
A26: Payment fee fixed $ | B26: 0.3 | C26: Per transaction
A27: Return rate % | B27: 0.26 | C27: US apparel avg ~26%. Tapstitch reviews cite sizing runs small — consider 0.30+
A28: Recovery on returns % | B28: 0 | C28: POD returns usually not resellable. 0% = total loss of goods.
A29: Discount uptake % | B29: 0.5 | C29: Share of orders using VOLT20 / WELCOME10
A30: Avg discount % | B30: 0.2 | C30: VOLT20 = 20%
A32: 3. ACQUISITION ASSUMPTIONS
A33: Assumption | B33: Value | C33: Source
A34: Meta CPC $ | B34: 0.55 | C34: Sourced: apparel CPC $0.45-0.58 (Triple Whale / Lebesgue, CY2025)
A35: Conversion rate % | B35: 0.01 | C35: Sourced: new-brand cold paid social 0.7-1.2%. 1.0% = midpoint
A36: TikTok referral fee % | B36: 0.06 | C36: Sourced: 6% US flat; some sources cite 8% apparel. Verify in Seller Center
A37: TikTok affiliate comm % | B37: 0.16 | C37: Sourced: fashion 15-18%; US avg 13.02%

Sheet Unit Economics
A1: Unit Economics by Product
A2: Everything here is formula-driven from Inputs. Fill the yellow cells there and this populates.
A4: Product | B4: Net revenue | C4: Landed COGS | D4: Shipping | E4: Payment fees | F4: Returns cost | G4: CM2 ($) | H4: CM2 (%) | I4: Breakeven ROAS | J4: Allowable CAC | K4: Actual CAC @ CPC/CVR | L4: Profit / order
A5: =Inputs!A13 | B5: =Inputs!B13*(1-Inputs!$B$29*Inputs!$B$30) | C5: =Inputs!C13*Inputs!D13+Inputs!E13*Inputs!F13+Inputs!I13 | D5: =Inputs!G13+MAX(0,Inputs!C13-1)*Inputs!H13 | E5: =B5*Inputs!$B$25+Inputs!$B$26 | F5: =Inputs!$B$27*(C5+D5)*(1-Inputs!$B$28) | G5: =B5-C5-D5-E5-F5 | H5: =IFERROR(G5/B5,0) | I5: =IFERROR(1/H5,0) | J5: =G5 | K5: =IFERROR(Inputs!$B$34/Inputs!$B$35,0) | L5: =G5-K5
A6: =Inputs!A14 | B6: =Inputs!B14*(1-Inputs!$B$29*Inputs!$B$30) | C6: =Inputs!C14*Inputs!D14+Inputs!E14*Inputs!F14+Inputs!I14 | D6: =Inputs!G14+MAX(0,Inputs!C14-1)*Inputs!H14 | E6: =B6*Inputs!$B$25+Inputs!$B$26 | F6: =Inputs!$B$27*(C6+D6)*(1-Inputs!$B$28) | G6: =B6-C6-D6-E6-F6 | H6: =IFERROR(G6/B6,0) | I6: =IFERROR(1/H6,0) | J6: =G6 | K6: =IFERROR(Inputs!$B$34/Inputs!$B$35,0) | L6: =G6-K6
A7: =Inputs!A15 | B7: =Inputs!B15*(1-Inputs!$B$29*Inputs!$B$30) | C7: =Inputs!C15*Inputs!D15+Inputs!E15*Inputs!F15+Inputs!I15 | D7: =Inputs!G15+MAX(0,Inputs!C15-1)*Inputs!H15 | E7: =B7*Inputs!$B$25+Inputs!$B$26 | F7: =Inputs!$B$27*(C7+D7)*(1-Inputs!$B$28) | G7: =B7-C7-D7-E7-F7 | H7: =IFERROR(G7/B7,0) | I7: =IFERROR(1/H7,0) | J7: =G7 | K7: =IFERROR(Inputs!$B$34/Inputs!$B$35,0) | L7: =G7-K7
A8: =Inputs!A16 | B8: =Inputs!B16*(1-Inputs!$B$29*Inputs!$B$30) | C8: =Inputs!C16*Inputs!D16+Inputs!E16*Inputs!F16+Inputs!I16 | D8: =Inputs!G16+MAX(0,Inputs!C16-1)*Inputs!H16 | E8: =B8*Inputs!$B$25+Inputs!$B$26 | F8: =Inputs!$B$27*(C8+D8)*(1-Inputs!$B$28) | G8: =B8-C8-D8-E8-F8 | H8: =IFERROR(G8/B8,0) | I8: =IFERROR(1/H8,0) | J8: =G8 | K8: =IFERROR(Inputs!$B$34/Inputs!$B$35,0) | L8: =G8-K8
A9: =Inputs!A17 | B9: =Inputs!B17*(1-Inputs!$B$29*Inputs!$B$30) | C9: =Inputs!C17*Inputs!D17+Inputs!E17*Inputs!F17+Inputs!I17 | D9: =Inputs!G17+MAX(0,Inputs!C17-1)*Inputs!H17 | E9: =B9*Inputs!$B$25+Inputs!$B$26 | F9: =Inputs!$B$27*(C9+D9)*(1-Inputs!$B$28) | G9: =B9-C9-D9-E9-F9 | H9: =IFERROR(G9/B9,0) | I9: =IFERROR(1/H9,0) | J9: =G9 | K9: =IFERROR(Inputs!$B$34/Inputs!$B$35,0) | L9: =G9-K9
A10: =Inputs!A18 | B10: =Inputs!B18*(1-Inputs!$B$29*Inputs!$B$30) | C10: =Inputs!C18*Inputs!D18+Inputs!E18*Inputs!F18+Inputs!I18 | D10: =Inputs!G18+MAX(0,Inputs!C18-1)*Inputs!H18 | E10: =B10*Inputs!$B$25+Inputs!$B$26 | F10: =Inputs!$B$27*(C10+D10)*(1-Inputs!$B$28) | G10: =B10-C10-D10-E10-F10 | H10: =IFERROR(G10/B10,0) | I10: =IFERROR(1/H10,0) | J10: =G10 | K10: =IFERROR(Inputs!$B$34/Inputs!$B$35,0) | L10: =G10-K10
A11: =Inputs!A19 | B11: =Inputs!B19*(1-Inputs!$B$29*Inputs!$B$30) | C11: =Inputs!C19*Inputs!D19+Inputs!E19*Inputs!F19+Inputs!I19 | D11: =Inputs!G19+MAX(0,Inputs!C19-1)*Inputs!H19 | E11: =B11*Inputs!$B$25+Inputs!$B$26 | F11: =Inputs!$B$27*(C11+D11)*(1-Inputs!$B$28) | G11: =B11-C11-D11-E11-F11 | H11: =IFERROR(G11/B11,0) | I11: =IFERROR(1/H11,0) | J11: =G11 | K11: =IFERROR(Inputs!$B$34/Inputs!$B$35,0) | L11: =G11-K11
A14: HOW TO READ THIS
A15: CM2 (%) | B15: Contribution margin before ad spend. Sourced threshold: below 30% "paid acquisition gets very hard".
A16: Breakeven ROAS | B16: =1 / CM2%. The return on ad spend you must beat just to not lose money.
A17: Allowable CAC | B17: The most you can pay to acquire one order and break even. Equals CM2.
A18: Actual CAC | B18: =CPC / conversion rate. What Meta will actually charge you at the assumed inputs.
A19: Profit / order | B19: Allowable CAC minus Actual CAC. NEGATIVE means you lose money on every order sold.

Sheet Revenue Target
A1: Revenue Target Model
A2: What $250k/month actually requires, using the unit economics from the previous sheet.
A4: Target monthly revenue | B4: 250000 | C4: Change this to model any target
A5: Blended AOV | B5: =IFERROR(AVERAGE('Unit Economics'!B5:B11),0) | C5: Average net revenue across catalogue. Raising this is the highest-leverage lever.
A6: Blended CM2 per order | B6: =IFERROR(AVERAGE('Unit Economics'!G5:G11),0)
A7: Blended CM2 % | B7: =IFERROR(B6/B5,0)
A9: VOLUME REQUIRED
A10: Orders per month | B10: =IFERROR(B4/B5,0)
A11: Orders per day | B11: =IFERROR(B10/30,0)
A12: Sessions/mo @ 0.7% CVR | B12: =IFERROR(B10/0.007,0) | C12: Sourced: new-brand cold paid social converts 0.7-1.2%
A13: Sessions/mo @ 1.0% CVR | B13: =IFERROR(B10/0.010,0)
A14: Sessions/mo @ 2.0% CVR | B14: =IFERROR(B10/0.020,0)
A16: PAID ACQUISITION OUTCOME
A17: Actual CAC (CPC / CVR) | B17: =IFERROR(Inputs!B34/Inputs!B35,0)
A18: Ad spend to hit target | B18: =IFERROR(B10*B17,0)
A19: Contribution generated | B19: =IFERROR(B10*B6,0)
A20: NET PROFIT / (LOSS) | B20: =B19-B18
A21: Achieved ROAS | B21: =IFERROR(B4/B18,0)
A22: Breakeven ROAS required | B22: =IFERROR(1/B7,0)
A24: TIKTOK SHOP ALTERNATIVE
A25: Platform take (referral + affiliate) | B25: =Inputs!B36+Inputs!B37
A26: Cost per order on TikTok | B26: =B5*(Inputs!B36+Inputs!B37)
A27: vs Meta actual CAC | B27: =B17-B26 | C27: Positive = TikTok Shop is cheaper per order than Meta at these assumptions
A29: Reality check: average active US TikTok Shop seller does $3,750/month GMV. Top 10% of sellers drive ~48% of all GMV.
A30: $250k/month is top-decile TikTok Shop performance and is a content-volume business (10+ creator videos/week at scale).

Sheet Sources
A1: Sources & Confidence
A2: Both research passes were run via web search only — direct page fetching was blocked by the network proxy. Figures are attributed but page methodology could not be verified.
A4: Figure | B4: Value | C4: Confidence | D4: Source
A5: Tapstitch activewear blank cost | B5: NOT FOUND | C5: n/a | D5: Prices render client-side; not in search index. Must pull from your account.
A6: Tapstitch US shipping | B6: $4.44 first item + $0.50 addl | C6: HIGH — first party | D6: tapstitch.com/help-center/faq/detail/shipping-cost
A7: Tapstitch print fee | B7: $2.99/area OR ~$5.00 one-side | C7: LOW — sources conflict | D7: michaelessek.com ; printsgram.com
A8: Tapstitch US tariff surcharge | B8: 20% duty on blank + $0.80-2.00/pc | C8: HIGH — first party | D8: support.tapstitch.com — U.S. Tariff Adjustment notice
A9: Tapstitch activewear launch | B9: March 2026 — US stocking partial | C9: HIGH — first party | D9: The Monthly Stitch, March 2026
A10: Apparel Meta CPC | B10: $0.45 - $0.58 | C10: MEDIUM | D10: Triple Whale ; Lebesgue
A11: New-brand cold paid social CVR | B11: 0.7% - 1.2% | C11: MEDIUM | D11: Eightx conversion-rate-by-traffic-source 2026
A12: Fashion Meta ROAS median | B12: 2.18x (top 10% = 6.0x) | C12: MEDIUM | D12: AdAmigo fashion ROAS benchmarks 2026
A13: US apparel return rate | B13: 20% - 40% (avg ~26%) | C13: MEDIUM | D13: NRF / Happy Returns ; Richpanel
A14: CM2 threshold for paid to work | B14: 30% minimum | C14: MEDIUM | D14: ask-luca.com contribution margin
A15: TikTok Shop referral fee | B15: 6% US flat (some cite 8% apparel) | C15: LOW — conflicting | D15: Fit Small Business ; Darkroom ; Dashboardly
... A17: Avg active TikTok Shop seller GMV | B17: $3,750/month | C17: MEDIUM | D17: Grey Journal 2026
