Workbook

Sheet Read Me
A1: Format R&D Tracker
A2: Metal Detectors Direct — Instagram growth, months 1–12
A5: HOW TO USE
A6: 1. | B6: Log every post in 'Post Log' — one row each. Fill only the BLUE columns; black columns calculate themselves.
A7: 2. | B7: Get Reach, 3s Retention, Follows, Saves, Shares and Comments from Instagram Insights (free, native).
A8: 3. | B8: 'Format Scorecard' updates automatically and tells you which formats to keep and which to kill.
A9: 4. | B9: Log creator loans in 'Seeding Tracker'. This is the paid-ads replacement — track it like a budget.
A11: THE RULES
A12: Sample size | B12: 5 posts minimum per format before judging. One hit and one flop are both noise.
A13: Metric that counts | B13: Follows per 1,000 reached — NOT views. A post can reach a million people and convert nobody.
A14: Hook check | B14: If 3s retention is under 50%, the hook failed and the format was never tested. Fix the hook, re-run.
A15: Kill criterion | B15: After 5 posts, if a format's follow rate is below a third of your best, retire it.
A16: Change one thing | B16: Never vary format, hook style and length at once — you learn nothing about what moved the number.
A18: COLOUR KEY
A19: Blue text | B19: You type here.
A20: Black text | B20: Calculated — do not overwrite.
A21: Pink italic row | B21: Example row showing expected format. Delete it before you start.
A23: NOTE | B23: Thresholds (5 posts, 50% retention, one-third of best) are starting points from the playbook.
B24: Replace them with your own baselines once the log has real data — they are assumptions, not facts.

Sheet 60-Day Plan
A1: 60-Day Posting Plan
A2: 191 original pieces in 60 days, each with a hook ready to shoot. Every piece cross-posts to Instagram Reels, TikTok, YouTube Shorts and Facebook Reels.
A3: Start date: | B3: 46244 | D3: Edit the yellow cell — all 191 dates follow from it.
A5: Day | B5: Date | C5: Slot | D5: Format | E5: Hook to use | F5: Source | G5: Shoot batch | H5: Posted? | I5: Notes
A6: 1 | B6: =IF($B$3="","",$B$3+A6-1) -> 46244 | C6: 1 | D6: 04 The Dig Reveal | E6: That tone means it's silver. | F6: Field | G6: S01
A7: 1 | B7: =IF($B$3="","",$B$3+A7-1) -> 46244 | C7: 2 | D7: 10 Detectorist Reacts | E7: He has no idea what he just dug up. | F7: Desk | G7: —
A8: 2 | B8: =IF($B$3="","",$B$3+A8-1) -> 46245 | C8: 1 | D8: 04 The Dig Reveal | E8: I almost walked past this. | F8: Field | G8: S01
A9: 2 | B9: =IF($B$3="","",$B$3+A9-1) -> 46245 | C9: 2 | D9: 01 The Depth Duel | E9: This $300 detector says there's nothing here. | F9: Field | G9: S01
A10: 3 | B10: =IF($B$3="","",$B$3+A10-1) -> 46246 | C10: 1 | D10: 04 The Dig Reveal | E10: Two inches down and it's already shining. | F10: Field | G10: S01
A11: 3 | B11: =IF($B$3="","",$B$3+A11-1) -> 46246 | C11: 2 | D11: 08 ASMR Restoration | E11: Sixty years of dirt. Watch. | F11: Desk | G11: —
A12: 4 | B12: =IF($B$3="","",$B$3+A12-1) -> 46247 | C12: 1 | D12: 04 The Dig Reveal | E12: That's not a bottle cap. | F12: Field | G12: S01
A13: 4 | B13: =IF($B$3="","",$B$3+A13-1) -> 46247 | C13: 2 | D13: 08 ASMR Restoration | E13: You will not believe what's under this. | F13: Desk | G13: —
A14: 5 | B14: =IF($B$3="","",$B$3+A14-1) -> 46248 | C14: 1 | D14: 09 Read the Tone | E14: Most people walk away from this sound. Don't. | F14: Field | G14: S01
A15: 5 | B15: =IF($B$3="","",$B$3+A15-1) -> 46248 | C15: 2 | D15: 10 Detectorist Reacts | E15: She thinks that's junk. It isn't. | F15: Desk | G15: —
A16: 6 | B16: =IF($B$3="","",$B$3+A16-1) -> 46249 | C16: 1 | D16: 08 ASMR Restoration | E16: No talking. Just cleaning. | F16: Desk | G16: —
A17: 6 | B17: =IF($B$3="","",$B$3+A17-1) -> 46249 | C17: 2 | D17: 01 The Depth Duel | E17: Same spot, same target. One of these finds it. | F17: Field | G17: S02
... A81: 30 | B81: =IF($B$3="","",$B$3+A81-1) -> 46273 | C81: 3 | D81: 08 ASMR Restoration | E81: Green to gold in three minutes. | F81: Desk | G81: —
A82: 31 | B82: =IF($B$3="","",$B$3+A82-1) -> 46274 | C82: 1 | D82: 07 Gold Hunt | E82: Third day on this creek. Today it finally paid. | F82: Field | G82: S07 | I82: Opportunistic — never force it
A83: 31 | B83: =IF($B$3="","",$B$3+A83-1) -> 46274 | C83: 2 | D83: 04 The Dig Reveal | E83: Watch the dirt come off this. | F83: Field | G83: S07
A84: 31 | B84: =IF($B$3="","",$B$3+A84-1) -> 46274 | C84: 3 | D84: 09 Read the Tone | E84: That flutter means it's sitting on edge. | F84: Field | G84: S07
A85: 32 | B85: =IF($B$3="","",$B$3+A85-1) -> 46275 | C85: 1 | D85: 04 The Dig Reveal | E85: Bottle cap. Bottle cap. Bottle cap. Oh. | F85: Field | G85: S07
A86: 32 | B86: =IF($B$3="","",$B$3+A86-1) -> 46275 | C86: 2 | D86: 10 Detectorist Reacts | E86: Watch his face when he realises. | F86: Desk | G86: —
A87: 32 | B87: =IF($B$3="","",$B$3+A87-1) -> 46275 | C87: 3 | D87: 08 ASMR Restoration | E87: Sixty years of dirt. Watch. | F87: Desk | G87: —
A88: 33 | B88: =IF($B$3="","",$B$3+A88-1) -> 46276 | C88: 1 | D88: 04 The Dig Reveal | E88: This ground's been hunted a thousand times. | F88: Field | G88: S07
A89: 33 | B89: =IF($B$3="","",$B$3+A89-1) -> 46276 | C89: 2 | D89: 12 Detector vs Detector | E89: The cheaper one won. I did not expect that. | F89: Field | G89: S07
A90: 33 | B90: =IF($B$3="","",$B$3+A90-1) -> 46276 | C90: 3 | D90: 09 Read the Tone | E90: One sound, two very different outcomes. | F90: Field | G90: S07
A91: 34 | B91: =IF($B$3="","",$B$3+A91-1) -> 46277 | C91: 1 | D91: 04 The Dig Reveal | E91: That tone means it's silver. | F91: Field | G91: S07
A92: 34 | B92: =IF($B$3="","",$B$3+A92-1) -> 46277 | C92: 2 | D92: 08 ASMR Restoration | E92: You will not believe what's under this. | F92: Desk | G92: —
A93: 34 | B93: =IF($B$3="","",$B$3+A93-1) -> 46277 | C93: 3 | D93: 10 Detectorist Reacts | E93: I've been sent a hundred of these. This one's different. | F93: Desk | G93: —
A94: 35 | B94: =IF($B$3="","",$B$3+A94-1) -> 46278 | C94: 1 | D94: 04 The Dig Reveal | E94: I almost walked past this. | F94: Field | G94: S07
... A96: 35 | B96: =IF($B$3="","",$B$3+A96-1) -> 46278 | C96: 3 | D96: 09 Read the Tone | E96: Your detector is telling you something. Here's what. | F96: Field | G96: S07
A97: 36 | B97: =IF($B$3="","",$B$3+A97-1) -> 46279 | C97: 1 | D97: 07 Gold Hunt | E97: That's gold. That's actually gold. | F97: Field | G97: S08 | I97: Opportunistic — never force it
A98: 36 | B98: =IF($B$3="","",$B$3+A98-1) -> 46279 | C98: 2 | D98: 08 ASMR Restoration | E98: No talking. Just cleaning. | F98: Desk | G98: —
A99: 36 | B99: =IF($B$3="","",$B$3+A99-1) -> 46279 | C99: 3 | D99: 03 You Pick the Spot | E99: You picked it. Now I have to dig it. | F99: Field | G99: S08
A100: 36 | B100: =IF($B$3="","",$B$3+A100-1) -> 46279 | C100: 4 | D100: 09 Read the Tone | E100: Most people walk away from this sound. Don't. | F100: Field | G100: S08
A101: 37 | B101: =IF($B$3="","",$B$3+A101-1) -> 46280 | C101: 1 | D101: 06 The Hour Haul | E101: Timer's on. Let's go. | F101: Field | G101: S08
A102: 37 | B102: =IF($B$3="","",$B$3+A102-1) -> 46280 | C102: 2 | D102: 08 ASMR Restoration | E102: Give it thirty seconds. | F102: Desk | G102: —
A103: 37 | B103: =IF($B$3="","",$B$3+A103-1) -> 46280 | C103: 3 | D103: 04 The Dig Reveal | E103: Two inches down and it's already shining. | F103: Field | G103: S08
A104: 37 | B104: =IF($B$3="","",$B$3+A104-1) -> 46280 | C104: 4 | D104: 02 Ground Scanner Reveal | E104: That red blob is eight feet down. | F104: Field | G104: S08
A105: 38 | B105: =IF($B$3="","",$B$3+A105-1) -> 46281 | C105: 1 | D105: 06 The Hour Haul | E105: One hour on this beach. Counter starts now. | F105: Field | G105: S08
A106: 38 | B106: =IF($B$3="","",$B$3+A106-1) -> 46281 | C106: 2 | D106: 10 Detectorist Reacts | E106: That is not what he thinks it is. | F106: Desk | G106: —
A107: 38 | B107: =IF($B$3="","",$B$3+A107-1) -> 46281 | C107: 3 | D107: 12 Detector vs Detector | E107: Which one would you actually buy? | F107: Field | G107: S08
A108: 38 | B108: =IF($B$3="","",$B$3+A108-1) -> 46281 | C108: 4 | D108: 02 Ground Scanner Reveal | E108: Most detectorists never see this screen. | F108: Field | G108: S08
A109: 39 | B109: =IF($B$3="","",$B$3+A109-1) -> 46282 | C109: 1 | D109: 08 ASMR Restoration | E109: This came out of the ground looking like a rock. | F109: Desk | G109: —
... A111: 39 | B111: =IF($B$3="","",$B$3+A111-1) -> 46282 | C111: 3 | D111: 04 The Dig Reveal | E111: That's not a bottle cap. | F111: Field | G111: S08
A112: 39 | B112: =IF($B$3="","",$B$3+A112-1) -> 46282 | C112: 4 | D112: 05 Ring Recovery | E112: She lost it in this lake eleven years ago. | F112: Field | G112: S08 | I112: Opportunistic — never force it
A113: 40 | B113: =IF($B$3="","",$B$3+A113-1) -> 46283 | C113: 1 | D113: 04 The Dig Reveal | E113: Listen to that. That's a good one. | F113: Field | G113: S08
A114: 40 | B114: =IF($B$3="","",$B$3+A114-1) -> 46283 | C114: 2 | D114: 01 The Depth Duel | E114: If your detector goes quiet here, it's lying to you. | F114: Field | G114: S08
A115: 40 | B115: =IF($B$3="","",$B$3+A115-1) -> 46283 | C115: 3 | D115: 10 Detectorist Reacts | E115: He has no idea what he just dug up. | F115: Desk | G115: —
A116: 40 | B116: =IF($B$3="","",$B$3+A116-1) -> 46283 | C116: 4 | D116: 09 Read the Tone | E116: If you hear this, dig it. | F116: Field | G116: S08
A117: 41 | B117: =IF($B$3="","",$B$3+A117-1) -> 46284 | C117: 1 | D117: 04 The Dig Reveal | E117: Twelve years detecting and this still got me. | F117: Field | G117: S09
A118: 41 | B118: =IF($B$3="","",$B$3+A118-1) -> 46284 | C118: 2 | D118: 10 Detectorist Reacts | E118: She thinks that's junk. It isn't. | F118: Desk | G118: —
A119: 41 | B119: =IF($B$3="","",$B$3+A119-1) -> 46284 | C119: 3 | D119: 09 Read the Tone | E119: This tone costs beginners their best finds. | F119: Field | G119: S09
A120: 41 | B120: =IF($B$3="","",$B$3+A120-1) -> 46284 | C120: 4 | D120: 03 You Pick the Spot | E120: Last time you chose wrong. Try again. | F120: Field | G120: S09
A121: 42 | B121: =IF($B$3="","",$B$3+A121-1) -> 46285 | C121: 1 | D121: 10 Detectorist Reacts | E121: This might be the find of the year. | F121: Desk | G121: —
A122: 42 | B122: =IF($B$3="","",$B$3+A122-1) -> 46285 | C122: 2 | D122: 08 ASMR Restoration | E122: Before and after, no filter. | F122: Desk | G122: —
A123: 42 | B123: =IF($B$3="","",$B$3+A123-1) -> 46285 | C123: 3 | D123: 11 Myth Test | E123: The rain myth, settled today. | F123: Field | G123: S09
A124: 42 | B124: =IF($B$3="","",$B$3+A124-1) -> 46285 | C124: 4 | D124: 07 Gold Hunt | E124: Everyone said this ground was worked out. | F124: Field | G124: S09 | I124: Opportunistic — never force it
A125: 43 | B125: =IF($B$3="","",$B$3+A125-1) -> 46286 | C125: 1 | D125: 10 Detectorist Reacts | E125: He nearly threw it back. | F125: Desk | G125: —
A126: 43 | B126: =IF($B$3="","",$B$3+A126-1) -> 46286 | C126: 2 | D126: 04 The Dig Reveal | E126: The signal was screaming. | F126: Field | G126: S09
A127: 43 | B127: =IF($B$3="","",$B$3+A127-1) -> 46286 | C127: 3 | D127: 02 Ground Scanner Reveal | E127: The machine drew this before I touched a shovel. | F127: Field | G127: S09
A128: 43 | B128: =IF($B$3="","",$B$3+A128-1) -> 46286 | C128: 4 | D128: 08 ASMR Restoration | E128: The first shine is the best part. | F128: Desk | G128: —
A129: 44 | B129: =IF($B$3="","",$B$3+A129-1) -> 46287 | C129: 1 | D129: 04 The Dig Reveal | E129: Whatever this is, it's deep. | F129: Field | G129: S09
A130: 44 | B130: =IF($B$3="","",$B$3+A130-1) -> 46287 | C130: 2 | D130: 02 Ground Scanner Reveal | E130: Scan first, dig second. Here's why. | F130: Field | G130: S09
A131: 44 | B131: =IF($B$3="","",$B$3+A131-1) -> 46287 | C131: 3 | D131: 07 Gold Hunt | E131: The pan doesn't lie. | F131: Field | G131: S09 | I131: Opportunistic — never force it
A132: 44 | B132: =IF($B$3="","",$B$3+A132-1) -> 46287 | C132: 4 | D132: 03 You Pick the Spot | E132: Grid's marked. Your move. | F132: Field | G132: S09
A133: 45 | B133: =IF($B$3="","",$B$3+A133-1) -> 46288 | C133: 1 | D133: 04 The Dig Reveal | E133: I've never dug one this clean. | F133: Field | G133: S09
A134: 45 | B134: =IF($B$3="","",$B$3+A134-1) -> 46288 | C134: 2 | D134: 09 Read the Tone | E134: Iron or silver? Listen again. | F134: Field | G134: S09
A135: 45 | B135: =IF($B$3="","",$B$3+A135-1) -> 46288 | C135: 3 | D135: 06 The Hour Haul | E135: Sixty minutes. Let's see what this sand is hiding. | F135: Field | G135: S09
A136: 45 | B136: =IF($B$3="","",$B$3+A136-1) -> 46288 | C136: 4 | D136: 05 Ring Recovery | E136: He proposed with it. Then the tide took it. | F136: Field | G136: S09 | I136: Opportunistic — never force it
A137: 46 | B137: =IF($B$3="","",$B$3+A137-1) -> 46289 | C137: 1 | D137: 09 Read the Tone | E137: That flutter means it's sitting on edge. | F137: Field | G137: S10
A138: 46 | B138: =IF($B$3="","",$B$3+A138-1) -> 46289 | C138: 2 | D138: 01 The Depth Duel | E138: This is why beginners quit. Watch. | F138: Field | G138: S10
A139: 46 | B139: =IF($B$3="","",$B$3+A139-1) -> 46289 | C139: 3 | D139: 05 Ring Recovery | E139: Forty minutes of searching for something this small. | F139: Field | G139: S10 | I139: Opportunistic — never force it
A140: 46 | B140: =IF($B$3="","",$B$3+A140-1) -> 46289 | C140: 4 | D140: 12 Detector vs Detector | E140: Identical conditions, honest result. | F140: Field | G140: S10
A141: 47 | B141: =IF($B$3="","",$B$3+A141-1) -> 46290 | C141: 1 | D141: 08 ASMR Restoration | E141: Green to gold in three minutes. | F141: Desk | G141: —
A142: 47 | B142: =IF($B$3="","",$B$3+A142-1) -> 46290 | C142: 2 | D142: 07 Gold Hunt | E142: Six hours for this, and worth every one. | F142: Field | G142: S10 | I142: Opportunistic — never force it
A143: 47 | B143: =IF($B$3="","",$B$3+A143-1) -> 46290 | C143: 3 | D143: 10 Detectorist Reacts | E143: Watch his face when he realises. | F143: Desk | G143: —
A144: 47 | B144: =IF($B$3="","",$B$3+A144-1) -> 46290 | C144: 4 | D144: 12 Detector vs Detector | E144: I tested both so you don't have to. | F144: Field | G144: S10
A145: 48 | B145: =IF($B$3="","",$B$3+A145-1) -> 46291 | C145: 1 | D145: 08 ASMR Restoration | E145: Sixty years of dirt. Watch. | F145: Desk | G145: —
A146: 48 | B146: =IF($B$3="","",$B$3+A146-1) -> 46291 | C146: 2 | D146: 06 The Hour Haul | E146: One hour, one detector, no cherry-picking. | F146: Field | G146: S10
A147: 48 | B147: =IF($B$3="","",$B$3+A147-1) -> 46291 | C147: 3 | D147: 02 Ground Scanner Reveal | E147: Something big is under here, and it isn't a pipe. | F147: Field | G147: S10
A148: 48 | B148: =IF($B$3="","",$B$3+A148-1) -> 46291 | C148: 4 | D148: 03 You Pick the Spot | E148: Most comments wins. I dig at dawn. | F148: Field | G148: S10
A149: 49 | B149: =IF($B$3="","",$B$3+A149-1) -> 46292 | C149: 1 | D149: 06 The Hour Haul | E149: Everything I find in an hour. Good and bad. | F149: Field | G149: S10
A150: 49 | B150: =IF($B$3="","",$B$3+A150-1) -> 46292 | C150: 2 | D150: 08 ASMR Restoration | E150: You will not believe what's under this. | F150: Desk | G150: —
A151: 49 | B151: =IF($B$3="","",$B$3+A151-1) -> 46292 | C151: 3 | D151: 10 Detectorist Reacts | E151: I've been sent a hundred of these. This one's different. | F151: Desk | G151: —
A152: 49 | B152: =IF($B$3="","",$B$3+A152-1) -> 46292 | C152: 4 | D152: 01 The Depth Duel | E152: Everyone's detector missed this. | F152: Field | G152: S10
A153: 50 | B153: =IF($B$3="","",$B$3+A153-1) -> 46293 | C153: 1 | D153: 10 Detectorist Reacts | E153: That is not what he thinks it is. | F153: Desk | G153: —
A154: 50 | B154: =IF($B$3="","",$B$3+A154-1) -> 46293 | C154: 2 | D154: 04 The Dig Reveal | E154: Watch the dirt come off this. | F154: Field | G154: S10
... A163: 52 | B163: =IF($B$3="","",$B$3+A163-1) -> 46295 | C163: 3 | D163: 03 You Pick the Spot | E163: Comment a number. I'm digging whichever square wins. | F163: Field | G163: S11
A164: 52 | B164: =IF($B$3="","",$B$3+A164-1) -> 46295 | C164: 4 | D164: 07 Gold Hunt | E164: That colour in the scoop. You know the one. | F164: Field | G164: S11 | I164: Opportunistic — never force it
A165: 53 | B165: =IF($B$3="","",$B$3+A165-1) -> 46296 | C165: 1 | D165: 10 Detectorist Reacts | E165: She thinks that's junk. It isn't. | F165: Desk | G165: —
A166: 53 | B166: =IF($B$3="","",$B$3+A166-1) -> 46296 | C166: 2 | D166: 03 You Pick the Spot | E166: Nine squares. You choose, I dig. | F166: Field | G166: S11
A167: 53 | B167: =IF($B$3="","",$B$3+A167-1) -> 46296 | C167: 3 | D167: 08 ASMR Restoration | E167: This came out of the ground looking like a rock. | F167: Desk | G167: —
A168: 53 | B168: =IF($B$3="","",$B$3+A168-1) -> 46296 | C168: 4 | D168: 09 Read the Tone | E168: One sound, two very different outcomes. | F168: Field | G168: S11
A169: 54 | B169: =IF($B$3="","",$B$3+A169-1) -> 46297 | C169: 1 | D169: 08 ASMR Restoration | E169: Before and after, no filter. | F169: Desk | G169: —
A170: 54 | B170: =IF($B$3="","",$B$3+A170-1) -> 46297 | C170: 2 | D170: 01 The Depth Duel | E170: This $300 detector says there's nothing here. | F170: Field | G170: S11
A171: 54 | B171: =IF($B$3="","",$B$3+A171-1) -> 46297 | C171: 3 | D171: 04 The Dig Reveal | E171: This ground's been hunted a thousand times. | F171: Field | G171: S11
A172: 54 | B172: =IF($B$3="","",$B$3+A172-1) -> 46297 | C172: 4 | D172: 07 Gold Hunt | E172: If this is what I think it is... | F172: Field | G172: S11 | I172: Opportunistic — never force it
A173: 55 | B173: =IF($B$3="","",$B$3+A173-1) -> 46298 | C173: 1 | D173: 06 The Hour Haul | E173: Timer's on. Let's go. | F173: Field | G173: S11
A174: 55 | B174: =IF($B$3="","",$B$3+A174-1) -> 46298 | C174: 2 | D174: 10 Detectorist Reacts | E174: This might be the find of the year. | F174: Desk | G174: —
...

Sheet Hook Bank
A1: Hook Bank
A2: The first three seconds decide reach. With no ad spend, the hook is the only reach lever you have. Add your own as you learn what lands — the plan cycles through these.
A4: Format | B4: # | C4: Hook
A5: 01 The Depth Duel | B5: 1 | C5: This $300 detector says there's nothing here.
B6: 2 | C6: Same spot, same target. One of these finds it.
B7: 3 | C7: I buried this at four feet. Let's see which one screams.
B8: 4 | C8: Your detector isn't broken. It's just shallow.
B9: 5 | C9: $300 versus $10,000, same patch of dirt.
B10: 6 | C10: The cheap one walked straight over it.
B11: 7 | C11: Three detectors, one target, only one is honest.
B12: 8 | C12: If your detector goes quiet here, it's lying to you.
B13: 9 | C13: This is why beginners quit. Watch.
B14: 10 | C14: Everyone's detector missed this.
A15: 02 Ground Scanner Reveal | B15: 1 | C15: There's something two metres under this field.
B16: 2 | C16: The screen says metal. The ground says nothing.
B17: 3 | C17: This is what underground actually looks like.
B18: 4 | C18: That red blob is eight feet down.
B19: 5 | C19: Most detectorists never see this screen.
B20: 6 | C20: The machine drew this before I touched a shovel.
B21: 7 | C21: Scan first, dig second. Here's why.
B22: 8 | C22: Something big is under here, and it isn't a pipe.
B23: 9 | C23: I scanned before I dug. Here's what it showed.
B24: 10 | C24: Let's find out if the scanner was right.
A25: 03 You Pick the Spot | B25: 1 | C25: Comment a number. I'm digging whichever square wins.
B26: 2 | C26: Nine squares. You choose, I dig.
B27: 3 | C27: Pick one. I'll be back tomorrow with what's in it.
B28: 4 | C28: Half of you said square four. So square four it is.
B29: 5 | C29: You picked it. Now I have to dig it.
B30: 6 | C30: Last time you chose wrong. Try again.
B31: 7 | C31: Grid's marked. Your move.
B32: 8 | C32: Most comments wins. I dig at dawn.
A33: 04 The Dig Reveal | B33: 1 | C33: That tone means it's silver.
B34: 2 | C34: I almost walked past this.
B35: 3 | C35: Two inches down and it's already shining.
B36: 4 | C36: That's not a bottle cap.
B37: 5 | C37: Listen to that. That's a good one.
B38: 6 | C38: Twelve years detecting and this still got me.
B39: 7 | C39: The signal was screaming.
B40: 8 | C40: Whatever this is, it's deep.
B41: 9 | C41: I've never dug one this clean.
B42: 10 | C42: Watch the dirt come off this.
B43: 11 | C43: Bottle cap. Bottle cap. Bottle cap. Oh.
B44: 12 | C44: This ground's been hunted a thousand times.
A45: 05 Ring Recovery | B45: 1 | C45: She lost it in this lake eleven years ago.
B46: 2 | C46: He proposed with it. Then the tide took it.
B47: 3 | C47: Forty minutes of searching for something this small.
B48: 4 | C48: She'd already given up on it.
B49: 5 | C49: This is the call every detectorist waits for.
B50: 6 | C50: Twenty years married. Lost it in one afternoon.
A51: 06 The Hour Haul | B51: 1 | C51: One hour on this beach. Counter starts now.
B52: 2 | C52: Sixty minutes. Let's see what this sand is hiding.
B53: 3 | C53: One hour, one detector, no cherry-picking.
B54: 4 | C54: Everything I find in an hour. Good and bad.
B55: 5 | C55: An hour here after a storm. This should be good.
B56: 6 | C56: How much can one hour actually pay?
B57: 7 | C57: Timer's on. Let's go.
A58: 07 Gold Hunt | B58: 1 | C58: Third day on this creek. Today it finally paid.
B59: 2 | C59: That's gold. That's actually gold.
B60: 3 | C60: Everyone said this ground was worked out.
B61: 4 | C61: The pan doesn't lie.
B62: 5 | C62: Six hours for this, and worth every one.
B63: 6 | C63: That colour in the scoop. You know the one.
B64: 7 | C64: If this is what I think it is...
A65: 08 ASMR Restoration | B65: 1 | C65: Sixty years of dirt. Watch.
B66: 2 | C66: You will not believe what's under this.
B67: 3 | C67: No talking. Just cleaning.
B68: 4 | C68: Give it thirty seconds.
B69: 5 | C69: This came out of the ground looking like a rock.
B70: 6 | C70: Before and after, no filter.
B71: 7 | C71: The first shine is the best part.
B72: 8 | C72: Green to gold in three minutes.
A73: 09 Read the Tone | B73: 1 | C73: Most people walk away from this sound. Don't.
B74: 2 | C74: If you hear this, dig it.
B75: 3 | C75: This tone costs beginners their best finds.
B76: 4 | C76: Iron or silver? Listen again.
B77: 5 | C77: That flutter means it's sitting on edge.
B78: 6 | C78: One sound, two very different outcomes.
B79: 7 | C79: Learn this tone and you'll double your finds.
B80: 8 | C80: Your detector is telling you something. Here's what.
A81: 10 Detectorist Reacts | B81: 1 | C81: He has no idea what he just dug up.
B82: 2 | C82: She thinks that's junk. It isn't.
B83: 3 | C83: This might be the find of the year.
B84: 4 | C84: He nearly threw it back.
B85: 5 | C85: Watch his face when he realises.
B86: 6 | C86: I've been sent a hundred of these. This one's different.
B87: 7 | C87: That is not what he thinks it is.
A88: 11 Myth Test | B88: 1 | C88: Everyone says you can't detect wet salt sand. Let's find out.
B89: 2 | C89: They told me this ground was dead. Testing that.
B90: 3 | C90: Does coil size actually matter? Real test.
B91: 4 | C91: The rain myth, settled today.
B92: 5 | C92: Everybody repeats this. Nobody's tested it.
B93: 6 | C93: I hope I'm wrong about this one.
B94: 7 | C94: Can it really punch through that? Honestly.
A95: 12 Detector vs Detector | B95: 1 | C95: Same ground, same target, two very different price tags.
B96: 2 | C96: Before you spend $2,000, watch this.
B97: 3 | C97: The cheaper one won. I did not expect that.
B98: 4 | C98: Which one would you actually buy?
B99: 5 | C99: Identical conditions, honest result.
B100: 6 | C100: I tested both so you don't have to.
B101: 7 | C101: The spec sheet said one thing. The dirt said another.

Sheet Post Log
A1: Post Log
A2: One row per post. Blue = you fill in. Black = calculated.
A4: Date | B4: Format | C4: Hook used | D4: Len (s) | E4: Platform | F4: Reach | G4: 3s Retention | H4: Follows | I4: Saves | J4: Shares | K4: Comments | L4: Follows /1k | M4: Saves /1k | N4: Hook verdict
A5: 2026-09-01 | B5: 04 The Dig Reveal | C5: That tone means it's silver. | D5: 18 | E5: Instagram | F5: 42000 | G5: 0.61 | H5: 310 | I5: 540 | J5: 220 | K5: 95 | L5: =IFERROR(H5/F5*1000,"") -> 7.3809524 | M5: =IFERROR(I5/F5*1000,"") -> 12.857143 | N5: =IF(G5="","",IF(G5>=0.5,"PASS","FIX HOOK")) -> PASS
L6: =IFERROR(H6/F6*1000,"") | M6: =IFERROR(I6/F6*1000,"") | N6: =IF(G6="","",IF(G6>=0.5,"PASS","FIX HOOK"))
L7: =IFERROR(H7/F7*1000,"") | M7: =IFERROR(I7/F7*1000,"") | N7: =IF(G7="","",IF(G7>=0.5,"PASS","FIX HOOK"))
L8: =IFERROR(H8/F8*1000,"") | M8: =IFERROR(I8/F8*1000,"") | N8: =IF(G8="","",IF(G8>=0.5,"PASS","FIX HOOK"))
L9: =IFERROR(H9/F9*1000,"") | M9: =IFERROR(I9/F9*1000,"") | N9: =IF(G9="","",IF(G9>=0.5,"PASS","FIX HOOK"))
L10: =IFERROR(H10/F10*1000,"") | M10: =IFERROR(I10/F10*1000,"") | N10: =IF(G10="","",IF(G10>=0.5,"PASS","FIX HOOK"))
L11: =IFERROR(H11/F11*1000,"") | M11: =IFERROR(I11/F11*1000,"") | N11: =IF(G11="","",IF(G11>=0.5,"PASS","FIX HOOK"))
L12: =IFERROR(H12/F12*1000,"") | M12: =IFERROR(I12/F12*1000,"") | N12: =IF(G12="","",IF(G12>=0.5,"PASS","FIX HOOK"))
L13: =IFERROR(H13/F13*1000,"") | M13: =IFERROR(I13/F13*1000,"") | N13: =IF(G13="","",IF(G13>=0.5,"PASS","FIX HOOK"))
L14: =IFERROR(H14/F14*1000,"") | M14: =IFERROR(I14/F14*1000,"") | N14: =IF(G14="","",IF(G14>=0.5,"PASS","FIX HOOK"))
L15: =IFERROR(H15/F15*1000,"") | M15: =IFERROR(I15/F15*1000,"") | N15: =IF(G15="","",IF(G15>=0.5,"PASS","FIX HOOK"))
L16: =IFERROR(H16/F16*1000,"") | M16: =IFERROR(I16/F16*1000,"") | N16: =IF(G16="","",IF(G16>=0.5,"PASS","FIX HOOK"))
L17: =IFERROR(H17/F17*1000,"") | M17: =IFERROR(I17/F17*1000,"") | N17: =IF(G17="","",IF(G17>=0.5,"PASS","FIX HOOK"))
... L500: =IFERROR(H500/F500*1000,"") | M500: =IFERROR(I500/F500*1000,"") | N500: =IF(G500="","",IF(G500>=0.5,"PASS","FIX HOOK"))

Sheet Format Scorecard
A1: Format Scorecard
A2: Updates automatically from Post Log. Judge each tier on its own job.
A4: Format | B4: Tier | C4: Posts | D4: Follows /1k | E4: Saves /1k | F4: Total reach | G4: Verdict
A5: 01 The Depth Duel | B5: A | C5: =COUNTIF('Post Log'!$B$5:$B$500,$A5) -> 0 | D5: =IFERROR(SUMIF('Post Log'!$B$5:$B$500,$A5,'Post Log'!$H$5:$H$500)/SUMIF('Post Log'!$B$5:$B$500,$A5,'Post Log'!$F$5:$F$500)*1000,"") | E5: =IFERROR(SUMIF('Post Log'!$B$5:$B$500,$A5,'Post Log'!$I$5:$I$500)/SUMIF('Post Log'!$B$5:$B$500,$A5,'Post Log'!$F$5:$F$500)*1000,"") | F5: =SUMIF('Post Log'!$B$5:$B$500,$A5,'Post Log'!$F$5:$F$500) -> 0 | G5: =IF(C5<5,"Collecting ("&C5&"/5)",IF(N($D$18)=0,"No data",IF(D5>=$D$18*0.33,"KEEP","KILL — reallocate"))) -> Collecting (0/5)
A6: 02 Ground Scanner Reveal | B6: A | C6: =COUNTIF('Post Log'!$B$5:$B$500,$A6) -> 0 | D6: =IFERROR(SUMIF('Post Log'!$B$5:$B$500,$A6,'Post Log'!$H$5:$H$500)/SUMIF('Post Log'!$B$5:$B$500,$A6,'Post Log'!$F$5:$F$500)*1000,"") | E6: =IFERROR(SUMIF('Post Log'!$B$5:$B$500,$A6,'Post Log'!$I$5:$I$500)/SUMIF('Post Log'!$B$5:$B$500,$A6,'Post Log'!$F$5:$F$500)*1000,"") | F6: =SUMIF('Post Log'!$B$5:$B$500,$A6,'Post Log'!$F$5:$F$500) -> 0 | G6: =IF(C6<5,"Collecting ("&C6&"/5)",IF(N($D$18)=0,"No data",IF(D6>=$D$18*0.33,"KEEP","KILL — reallocate"))) -> Collecting (0/5)
A7: 03 You Pick the Spot | B7: A | C7: =COUNTIF('Post Log'!$B$5:$B$500,$A7) -> 0 | D7: =IFERROR(SUMIF('Post Log'!$B$5:$B$500,$A7,'Post Log'!$H$5:$H$500)/SUMIF('Post Log'!$B$5:$B$500,$A7,'Post Log'!$F$5:$F$500)*1000,"") | E7: =IFERROR(SUMIF('Post Log'!$B$5:$B$500,$A7,'Post Log'!$I$5:$I$500)/SUMIF('Post Log'!$B$5:$B$500,$A7,'Post Log'!$F$5:$F$500)*1000,"") | F7: =SUMIF('Post Log'!$B$5:$B$500,$A7,'Post Log'!$F$5:$F$500) -> 0 | G7: =IF(C7<5,"Collecting ("&C7&"/5)",IF(N($D$18)=0,"No data",IF(D7>=$D$18*0.33,"KEEP","KILL — reallocate"))) -> Collecting (0/5)
A8: 04 The Dig Reveal | B8: B | C8: =COUNTIF('Post Log'!$B$5:$B$500,$A8) -> 1 | D8: =IFERROR(SUMIF('Post Log'!$B$5:$B$500,$A8,'Post Log'!$H$5:$H$500)/SUMIF('Post Log'!$B$5:$B$500,$A8,'Post Log'!$F$5:$F$500)*1000,"") -> 7.3809524 | E8: =IFERROR(SUMIF('Post Log'!$B$5:$B$500,$A8,'Post Log'!$I$5:$I$500)/SUMIF('Post Log'!$B$5:$B$500,$A8,'Post Log'!$F$5:$F$500)*1000,"") -> 12.857143 | F8: =SUMIF('Post Log'!$B$5:$B$500,$A8,'Post Log'!$F$5:$F$500) -> 42000 | G8: =IF(C8<5,"Collecting ("&C8&"/5)",IF(N($D$18)=0,"No data",IF(D8>=$D$18*0.33,"KEEP","KILL — reallocate"))) -> Collecting (1/5)
A9: 05 Ring Recovery | B9: B | C9: =COUNTIF('Post Log'!$B$5:$B$500,$A9) -> 0 | D9: =IFERROR(SUMIF('Post Log'!$B$5:$B$500,$A9,'Post Log'!$H$5:$H$500)/SUMIF('Post Log'!$B$5:$B$500,$A9,'Post Log'!$F$5:$F$500)*1000,"") | E9: =IFERROR(SUMIF('Post Log'!$B$5:$B$500,$A9,'Post Log'!$I$5:$I$500)/SUMIF('Post Log'!$B$5:$B$500,$A9,'Post Log'!$F$5:$F$500)*1000,"") | F9: =SUMIF('Post Log'!$B$5:$B$500,$A9,'Post Log'!$F$5:$F$500) -> 0 | G9: =IF(C9<5,"Collecting ("&C9&"/5)",IF(N($D$18)=0,"No data",IF(D9>=$D$18*0.33,"KEEP","KILL — reallocate"))) -> Collecting (0/5)
A10: 06 The Hour Haul | B10: B | C10: =COUNTIF('Post Log'!$B$5:$B$500,$A10) -> 0 | D10: =IFERROR(SUMIF('Post Log'!$B$5:$B$500,$A10,'Post Log'!$H$5:$H$500)/SUMIF('Post Log'!$B$5:$B$500,$A10,'Post Log'!$F$5:$F$500)*1000,"") | E10: =IFERROR(SUMIF('Post Log'!$B$5:$B$500,$A10,'Post Log'!$I$5:$I$500)/SUMIF('Post Log'!$B$5:$B$500,$A10,'Post Log'!$F$5:$F$500)*1000,"") | F10: =SUMIF('Post Log'!$B$5:$B$500,$A10,'Post Log'!$F$5:$F$500) -> 0 | G10: =IF(C10<5,"Collecting ("&C10&"/5)",IF(N($D$18)=0,"No data",IF(D10>=$D$18*0.33,"KEEP","KILL — reallocate"))) -> Collecting (0/5)
A11: 07 Gold Hunt | B11: B | C11: =COUNTIF('Post Log'!$B$5:$B$500,$A11) -> 0 | D11: =IFERROR(SUMIF('Post Log'!$B$5:$B$500,$A11,'Post Log'!$H$5:$H$500)/SUMIF('Post Log'!$B$5:$B$500,$A11,'Post Log'!$F$5:$F$500)*1000,"") | E11: =IFERROR(SUMIF('Post Log'!$B$5:$B$500,$A11,'Post Log'!$I$5:$I$500)/SUMIF('Post Log'!$B$5:$B$500,$A11,'Post Log'!$F$5:$F$500)*1000,"") | F11: =SUMIF('Post Log'!$B$5:$B$500,$A11,'Post Log'!$F$5:$F$500) -> 0 | G11: =IF(C11<5,"Collecting ("&C11&"/5)",IF(N($D$18)=0,"No data",IF(D11>=$D$18*0.33,"KEEP","KILL — reallocate"))) -> Collecting (0/5)
A12: 08 ASMR Restoration | B12: C | C12: =COUNTIF('Post Log'!$B$5:$B$500,$A12) -> 0 | D12: =IFERROR(SUMIF('Post Log'!$B$5:$B$500,$A12,'Post Log'!$H$5:$H$500)/SUMIF('Post Log'!$B$5:$B$500,$A12,'Post Log'!$F$5:$F$500)*1000,"") | E12: =IFERROR(SUMIF('Post Log'!$B$5:$B$500,$A12,'Post Log'!$I$5:$I$500)/SUMIF('Post Log'!$B$5:$B$500,$A12,'Post Log'!$F$5:$F$500)*1000,"") | F12: =SUMIF('Post Log'!$B$5:$B$500,$A12,'Post Log'!$F$5:$F$500) -> 0 | G12: =IF(C12<5,"Collecting ("&C12&"/5)",IF(N($D$18)=0,"No data",IF(D12>=$D$18*0.33,"KEEP","KILL — reallocate"))) -> Collecting (0/5)
A13: 09 Read the Tone | B13: C | C13: =COUNTIF('Post Log'!$B$5:$B$500,$A13) -> 0 | D13: =IFERROR(SUMIF('Post Log'!$B$5:$B$500,$A13,'Post Log'!$H$5:$H$500)/SUMIF('Post Log'!$B$5:$B$500,$A13,'Post Log'!$F$5:$F$500)*1000,"") | E13: =IFERROR(SUMIF('Post Log'!$B$5:$B$500,$A13,'Post Log'!$I$5:$I$500)/SUMIF('Post Log'!$B$5:$B$500,$A13,'Post Log'!$F$5:$F$500)*1000,"") | F13: =SUMIF('Post Log'!$B$5:$B$500,$A13,'Post Log'!$F$5:$F$500) -> 0 | G13: =IF(C13<5,"Collecting ("&C13&"/5)",IF(N($D$18)=0,"No data",IF(D13>=$D$18*0.33,"KEEP","KILL — reallocate"))) -> Collecting (0/5)
A14: 10 Detectorist Reacts | B14: D | C14: =COUNTIF('Post Log'!$B$5:$B$500,$A14) -> 0 | D14: =IFERROR(SUMIF('Post Log'!$B$5:$B$500,$A14,'Post Log'!$H$5:$H$500)/SUMIF('Post Log'!$B$5:$B$500,$A14,'Post Log'!$F$5:$F$500)*1000,"") | E14: =IFERROR(SUMIF('Post Log'!$B$5:$B$500,$A14,'Post Log'!$I$5:$I$500)/SUMIF('Post Log'!$B$5:$B$500,$A14,'Post Log'!$F$5:$F$500)*1000,"") | F14: =SUMIF('Post Log'!$B$5:$B$500,$A14,'Post Log'!$F$5:$F$500) -> 0 | G14: =IF(C14<5,"Collecting ("&C14&"/5)",IF(N($D$18)=0,"No data",IF(D14>=$D$18*0.33,"KEEP","KILL — reallocate"))) -> Collecting (0/5)
A15: 11 Myth Test | B15: D | C15: =COUNTIF('Post Log'!$B$5:$B$500,$A15) -> 0 | D15: =IFERROR(SUMIF('Post Log'!$B$5:$B$500,$A15,'Post Log'!$H$5:$H$500)/SUMIF('Post Log'!$B$5:$B$500,$A15,'Post Log'!$F$5:$F$500)*1000,"") | E15: =IFERROR(SUMIF('Post Log'!$B$5:$B$500,$A15,'Post Log'!$I$5:$I$500)/SUMIF('Post Log'!$B$5:$B$500,$A15,'Post Log'!$F$5:$F$500)*1000,"") | F15: =SUMIF('Post Log'!$B$5:$B$500,$A15,'Post Log'!$F$5:$F$500) -> 0 | G15: =IF(C15<5,"Collecting ("&C15&"/5)",IF(N($D$18)=0,"No data",IF(D15>=$D$18*0.33,"KEEP","KILL — reallocate"))) -> Collecting (0/5)
A16: 12 Detector vs Detector | B16: D | C16: =COUNTIF('Post Log'!$B$5:$B$500,$A16) -> 0 | D16: =IFERROR(SUMIF('Post Log'!$B$5:$B$500,$A16,'Post Log'!$H$5:$H$500)/SUMIF('Post Log'!$B$5:$B$500,$A16,'Post Log'!$F$5:$F$500)*1000,"") | E16: =IFERROR(SUMIF('Post Log'!$B$5:$B$500,$A16,'Post Log'!$I$5:$I$500)/SUMIF('Post Log'!$B$5:$B$500,$A16,'Post Log'!$F$5:$F$500)*1000,"") | F16: =SUMIF('Post Log'!$B$5:$B$500,$A16,'Post Log'!$F$5:$F$500) -> 0 | G16: =IF(C16<5,"Collecting ("&C16&"/5)",IF(N($D$18)=0,"No data",IF(D16>=$D$18*0.33,"KEEP","KILL — reallocate"))) -> Collecting (0/5)
A18: Best follow rate | D18: =IFERROR(MAX(D5:D16),0) -> 7.3809524 | E18: Kill threshold = one third of this. Assumption from the playbook — replace once you have real baselines.
A20: Judge each tier on its own job:
A21: A · Signature | B21: Follows per 1k. Your growth engine — should post your best follow rate.
A22: B · Core | B22: Consistency and volume. Baseline cadence, keeps the account alive daily.
A23: C · Retention | B23: Saves per 1k. Ranking support and all-weather output.
A24: D · Reach | B24: Comments, and enquiries for #12. Distribution signals and relationships.

Sheet Seeding Tracker
A1: Seeding Tracker
A2: Equipment loans replace the ad budget — track them like spend. Target 5K–100K followers. Ask for a COLLAB post, not a mention.
A4: Creator | B4: Handle | C4: Followers | D4: Gear lent | E4: Date out | F4: Status | G4: Collab posted? | H4: Reach delivered | I4: Follows gained | J4: Enquiries | K4: Disclosure OK? | L4: Verdict
A5: Jane Doe | B5: @example_detects | C5: 24000 | D5: AlgoForce entry unit (loan) | E5: 2026-10-05 | F5: Delivered | G5: Yes | H5: 180000 | I5: 940 | J5: 6 | K5: Yes | L5: =IF(A5="","",IF(G5<>"Yes","Awaiting collab post",IF(K5<>"Yes","FIX DISCLOSURE",IF(N(I5)>=250,"Convert to gift","Keep on loan")))) -> Convert to gift
L6: =IF(A6="","",IF(G6<>"Yes","Awaiting collab post",IF(K6<>"Yes","FIX DISCLOSURE",IF(N(I6)>=250,"Convert to gift","Keep on loan"))))
L7: =IF(A7="","",IF(G7<>"Yes","Awaiting collab post",IF(K7<>"Yes","FIX DISCLOSURE",IF(N(I7)>=250,"Convert to gift","Keep on loan"))))
L8: =IF(A8="","",IF(G8<>"Yes","Awaiting collab post",IF(K8<>"Yes","FIX DISCLOSURE",IF(N(I8)>=250,"Convert to gift","Keep on loan"))))
L9: =IF(A9="","",IF(G9<>"Yes","Awaiting collab post",IF(K9<>"Yes","FIX DISCLOSURE",IF(N(I9)>=250,"Convert to gift","Keep on loan"))))
L10: =IF(A10="","",IF(G10<>"Yes","Awaiting collab post",IF(K10<>"Yes","FIX DISCLOSURE",IF(N(I10)>=250,"Convert to gift","Keep on loan"))))
L11: =IF(A11="","",IF(G11<>"Yes","Awaiting collab post",IF(K11<>"Yes","FIX DISCLOSURE",IF(N(I11)>=250,"Convert to gift","Keep on loan"))))
L12: =IF(A12="","",IF(G12<>"Yes","Awaiting collab post",IF(K12<>"Yes","FIX DISCLOSURE",IF(N(I12)>=250,"Convert to gift","Keep on loan"))))
L13: =IF(A13="","",IF(G13<>"Yes","Awaiting collab post",IF(K13<>"Yes","FIX DISCLOSURE",IF(N(I13)>=250,"Convert to gift","Keep on loan"))))
L14: =IF(A14="","",IF(G14<>"Yes","Awaiting collab post",IF(K14<>"Yes","FIX DISCLOSURE",IF(N(I14)>=250,"Convert to gift","Keep on loan"))))
L15: =IF(A15="","",IF(G15<>"Yes","Awaiting collab post",IF(K15<>"Yes","FIX DISCLOSURE",IF(N(I15)>=250,"Convert to gift","Keep on loan"))))
L16: =IF(A16="","",IF(G16<>"Yes","Awaiting collab post",IF(K16<>"Yes","FIX DISCLOSURE",IF(N(I16)>=250,"Convert to gift","Keep on loan"))))
L17: =IF(A17="","",IF(G17<>"Yes","Awaiting collab post",IF(K17<>"Yes","FIX DISCLOSURE",IF(N(I17)>=250,"Convert to gift","Keep on loan"))))
... L120: =IF(A120="","",IF(G120<>"Yes","Awaiting collab post",IF(K120<>"Yes","FIX DISCLOSURE",IF(N(I120)>=250,"Convert to gift","Keep on loan"))))
